{
  "##choices#calibration_time": 10.0, 
  "##choices#cmd_key": "encode", 
  "##choices#compile_type": "dynamic", 
  "##choices#compiler_description_uoa": "gcc-4.9.0-auto", 
  "##choices#compiler_flags#base_opt": "-O3", 
  "##choices#compiler_flags#bool-conserve-stack": "-fno-conserve-stack", 
  "##choices#compiler_flags#bool-fast-math": "-ffast-math", 
  "##choices#compiler_flags#bool-graphite-identity": "-fgraphite-identity", 
  "##choices#compiler_flags#bool-guess-branch-probability": "-fguess-branch-probability", 
  "##choices#compiler_flags#bool-ipa-pta": "-fno-ipa-pta", 
  "##choices#compiler_flags#bool-ipa-reference": "-fno-ipa-reference", 
  "##choices#compiler_flags#bool-isolate-erroneous-paths-attribute": "-fisolate-erroneous-paths-attribute", 
  "##choices#compiler_flags#bool-loop-block": "-floop-block", 
  "##choices#compiler_flags#bool-sched-group-heuristic": "-fsched-group-heuristic", 
  "##choices#compiler_flags#bool-sched-spec": "-fsched-spec", 
  "##choices#compiler_flags#bool-sched-spec-load-dangerous": "-fsched-spec-load-dangerous", 
  "##choices#compiler_flags#bool-schedule-insns2": "-fno-schedule-insns2", 
  "##choices#compiler_flags#bool-tree-pta": "-ftree-pta", 
  "##choices#compiler_flags#bool-web": "-fweb", 
  "##choices#compiler_flags#param--falign-jumps=": "-falign-jumps=0", 
  "##choices#compiler_flags#param-align-threshold": "--param align-threshold=69", 
  "##choices#compiler_flags#param-asan-stack": "--param asan-stack=1", 
  "##choices#compiler_flags#param-asan-use-after-return": "--param asan-use-after-return=1", 
  "##choices#compiler_flags#param-gcse-cost-distance-ratio": "--param gcse-cost-distance-ratio=3", 
  "##choices#compiler_flags#param-gcse-unrestricted-cost": "--param gcse-unrestricted-cost=3", 
  "##choices#compiler_flags#param-hot-bb-frequency-fraction": "--param hot-bb-frequency-fraction=1590", 
  "##choices#compiler_flags#param-inline-unit-growth": "--param inline-unit-growth=25", 
  "##choices#compiler_flags#param-ipa-cp-eval-threshold": "--param ipa-cp-eval-threshold=297", 
  "##choices#compiler_flags#param-ipcp-unit-growth": "--param ipcp-unit-growth=15", 
  "##choices#compiler_flags#param-ira-max-loops-num": "--param ira-max-loops-num=22", 
  "##choices#compiler_flags#param-iv-consider-all-candidates-bound": "--param iv-consider-all-candidates-bound=2", 
  "##choices#compiler_flags#param-l2-cache-size": "--param l2-cache-size=281", 
  "##choices#compiler_flags#param-large-unit-insns": "--param large-unit-insns=10578", 
  "##choices#compiler_flags#param-max-cse-path-length": "--param max-cse-path-length=13", 
  "##choices#compiler_flags#param-max-fields-for-field-sensitive": "--param max-fields-for-field-sensitive=0", 
  "##choices#compiler_flags#param-max-goto-duplication-insns": "--param max-goto-duplication-insns=3", 
  "##choices#compiler_flags#param-max-last-value-rtl": "--param max-last-value-rtl=319", 
  "##choices#compiler_flags#param-max-tail-merge-iterations": "--param max-tail-merge-iterations=1", 
  "##choices#compiler_flags#param-min-spec-prob": "--param min-spec-prob=15", 
  "##choices#compiler_flags#param-omega-max-geqs": "--param omega-max-geqs=143", 
  "##choices#compiler_flags#param-sccvn-max-alias-queries-per-access": "--param sccvn-max-alias-queries-per-access=908", 
  "##choices#compiler_flags#param-scev-max-expr-complexity": "--param scev-max-expr-complexity=18", 
  "##choices#compiler_flags#param-selsched-insns-to-rename": "--param selsched-insns-to-rename=4", 
  "##choices#compiler_flags#param-sink-frequency-threshold": "--param sink-frequency-threshold=27", 
  "##choices#compiler_flags#param-tracer-min-branch-probability": "--param tracer-min-branch-probability=16", 
  "##choices#compiler_flags#param-vect-max-version-for-alias-checks": "--param vect-max-version-for-alias-checks=13", 
  "##choices#compiler_flags#param-vect-max-version-for-alignment-checks": "--param vect-max-version-for-alignment-checks=0", 
  "##choices#data_uoa": "gzip", 
  "##choices#dataset_file": "data.pgm", 
  "##choices#dataset_uoa": "image-pgm-clean-gray-square-600-450-8", 
  "##choices#device_id": "", 
  "##choices#host_os": "linux-32", 
  "##choices#module_uoa": "b0ac08fe1d3c2615", 
  "##choices#no_state_check": "yes", 
  "##choices#program_tags": "", 
  "##choices#repeat": 423, 
  "##choices#target": "", 
  "##choices#target_os": "linux-32", 
  "##choices#target_os_bits": "32"
}
