{
  "##choices#calibration_time": 10.0, 
  "##choices#cmd_key": "decode", 
  "##choices#compile_type": "dynamic", 
  "##choices#compiler_description_uoa": "gcc-4.9.0-auto", 
  "##choices#compiler_flags#base_opt": "-O3", 
  "##choices#compiler_flags#bool--fira-region=": "-fira-region=one", 
  "##choices#compiler_flags#bool-associative-math": "-fassociative-math", 
  "##choices#compiler_flags#bool-compare-elim": "-fno-compare-elim", 
  "##choices#compiler_flags#bool-conserve-stack": "-fconserve-stack", 
  "##choices#compiler_flags#bool-crossjumping": "-fno-crossjumping", 
  "##choices#compiler_flags#bool-dce": "-fno-dce", 
  "##choices#compiler_flags#bool-hoist-adjacent-loads": "-fno-hoist-adjacent-loads", 
  "##choices#compiler_flags#bool-inline": "-finline", 
  "##choices#compiler_flags#bool-peel-loops": "-fpeel-loops", 
  "##choices#compiler_flags#bool-reciprocal-math": "-fno-reciprocal-math", 
  "##choices#compiler_flags#bool-sched-interblock": "-fno-sched-interblock", 
  "##choices#compiler_flags#bool-sched-last-insn-heuristic": "-fno-sched-last-insn-heuristic", 
  "##choices#compiler_flags#bool-sched-spec-load": "-fno-sched-spec-load", 
  "##choices#compiler_flags#bool-sel-sched-pipelining-outer-loops": "-fsel-sched-pipelining-outer-loops", 
  "##choices#compiler_flags#bool-selective-scheduling2": "-fno-selective-scheduling2", 
  "##choices#compiler_flags#bool-strict-overflow": "-fstrict-overflow", 
  "##choices#compiler_flags#bool-tree-loop-distribute-patterns": "-fno-tree-loop-distribute-patterns", 
  "##choices#compiler_flags#bool-tree-loop-im": "-ftree-loop-im", 
  "##choices#compiler_flags#bool-tree-loop-vectorize": "-ftree-loop-vectorize", 
  "##choices#compiler_flags#bool-unswitch-loops": "-fno-unswitch-loops", 
  "##choices#compiler_flags#param--falign-labels=": "-falign-labels=0", 
  "##choices#compiler_flags#param-allow-packed-load-data-races": "--param allow-packed-load-data-races=1", 
  "##choices#compiler_flags#param-allow-store-data-races": "--param allow-store-data-races=1", 
  "##choices#compiler_flags#param-asan-stack": "--param asan-stack=1", 
  "##choices#compiler_flags#param-comdat-sharing-probability": "--param comdat-sharing-probability=21", 
  "##choices#compiler_flags#param-early-inlining-insns": "--param early-inlining-insns=14", 
  "##choices#compiler_flags#param-ipa-sra-ptr-growth-factor": "--param ipa-sra-ptr-growth-factor=2", 
  "##choices#compiler_flags#param-large-function-growth": "--param large-function-growth=31", 
  "##choices#compiler_flags#param-large-unit-insns": "--param large-unit-insns=8395", 
  "##choices#compiler_flags#param-max-completely-peel-loop-nest-depth": "--param max-completely-peel-loop-nest-depth=8", 
  "##choices#compiler_flags#param-max-delay-slot-insn-search": "--param max-delay-slot-insn-search=36", 
  "##choices#compiler_flags#param-max-early-inliner-iterations": "--param max-early-inliner-iterations=2", 
  "##choices#compiler_flags#param-max-iterations-to-track": "--param max-iterations-to-track=500", 
  "##choices#compiler_flags#param-max-modulo-backtrack-attempts": "--param max-modulo-backtrack-attempts=44", 
  "##choices#compiler_flags#param-max-sched-extend-regions-iters": "--param max-sched-extend-regions-iters=0", 
  "##choices#compiler_flags#param-max-stores-to-sink": "--param max-stores-to-sink=0", 
  "##choices#compiler_flags#param-omega-max-eqs": "--param omega-max-eqs=78", 
  "##choices#compiler_flags#param-partial-inlining-entry-probability": "--param partial-inlining-entry-probability=99", 
  "##choices#compiler_flags#param-sched-state-edge-prob-cutoff": "--param sched-state-edge-prob-cutoff=6", 
  "##choices#compiler_flags#param-sms-max-ii-factor": "--param sms-max-ii-factor=106", 
  "##choices#compiler_flags#param-tm-max-aggregate-size": "--param tm-max-aggregate-size=1", 
  "##choices#compiler_flags#param-vect-max-version-for-alignment-checks": "--param vect-max-version-for-alignment-checks=3", 
  "##choices#data_uoa": "zlib", 
  "##choices#dataset_file": "data", 
  "##choices#dataset_uoa": "txt-verse-novel-0001-deflated", 
  "##choices#device_id": "", 
  "##choices#host_os": "linux-32", 
  "##choices#module_uoa": "b0ac08fe1d3c2615", 
  "##choices#no_state_check": "yes", 
  "##choices#program_tags": "", 
  "##choices#repeat": 1101, 
  "##choices#target": "", 
  "##choices#target_os": "linux-32", 
  "##choices#target_os_bits": "32"
}
