{
  "##choices#calibration_time": 10.0, 
  "##choices#cmd_key": "encode", 
  "##choices#compile_type": "dynamic", 
  "##choices#compiler_description_uoa": "gcc-4.9.0-auto", 
  "##choices#compiler_flags#base_opt": "-O3", 
  "##choices#compiler_flags#bool--fira-algorithm=": "-fira-algorithm=CB", 
  "##choices#compiler_flags#bool--fira-region=": "-fira-region=all", 
  "##choices#compiler_flags#bool-conserve-stack": "-fconserve-stack", 
  "##choices#compiler_flags#bool-delete-null-pointer-checks": "-fno-delete-null-pointer-checks", 
  "##choices#compiler_flags#bool-devirtualize-speculatively": "-fdevirtualize-speculatively", 
  "##choices#compiler_flags#bool-float-store": "-fno-float-store", 
  "##choices#compiler_flags#bool-function-sections": "-ffunction-sections", 
  "##choices#compiler_flags#bool-ipa-cp-clone": "-fipa-cp-clone", 
  "##choices#compiler_flags#bool-ipa-sra": "-fipa-sra", 
  "##choices#compiler_flags#bool-ira-share-save-slots": "-fira-share-save-slots", 
  "##choices#compiler_flags#bool-sched-spec-load": "-fno-sched-spec-load", 
  "##choices#compiler_flags#bool-sched-spec-load-dangerous": "-fno-sched-spec-load-dangerous", 
  "##choices#compiler_flags#bool-sched2-use-superblocks": "-fno-sched2-use-superblocks", 
  "##choices#compiler_flags#bool-signed-zeros": "-fsigned-zeros", 
  "##choices#compiler_flags#bool-strict-aliasing": "-fno-strict-aliasing", 
  "##choices#compiler_flags#bool-trapping-math": "-fno-trapping-math", 
  "##choices#compiler_flags#bool-tree-builtin-call-dce": "-ftree-builtin-call-dce", 
  "##choices#compiler_flags#bool-tree-coalesce-vars": "-ftree-coalesce-vars", 
  "##choices#compiler_flags#bool-tree-copyrename": "-fno-tree-copyrename", 
  "##choices#compiler_flags#bool-variable-expansion-in-unroller": "-fvariable-expansion-in-unroller", 
  "##choices#compiler_flags#bool-web": "-fweb", 
  "##choices#data_uoa": "zlib", 
  "##choices#dataset_file": "data.wav", 
  "##choices#dataset_uoa": "audio-wav-0001", 
  "##choices#device_id": "", 
  "##choices#host_os": "linux-32", 
  "##choices#module_uoa": "b0ac08fe1d3c2615", 
  "##choices#no_state_check": "yes", 
  "##choices#program_tags": "", 
  "##choices#repeat": 46, 
  "##choices#target": "", 
  "##choices#target_os": "linux-32", 
  "##choices#target_os_bits": "32"
}
